README.md
setup.py
minipush/__init__.py
minipush/__main__.py
minipush/conf.py
minipush/conf_.py
minipush/cssmin.py
minipush/default_config.py
minipush/errors.py
minipush/jsmin.py
minipush/mp.py
minipush/push.py
minipush.egg-info/PKG-INFO
minipush.egg-info/SOURCES.txt
minipush.egg-info/dependency_links.txt
minipush.egg-info/top_level.txt