Metadata-Version: 2.1
Name: minipush
Version: 0.0.11
Summary: A package to minimize your scripts and stylesheets
Home-page: https://github.com/merlleu/minipush
Author: Rémi 'Mr e-RL'LANGDORPH
Author-email: r.langdorph@gmail.com
License: UNKNOWN
Platform: UNKNOWN
Classifier: Programming Language :: Python :: 3
Classifier: License :: OSI Approved :: MIT License
Classifier: Operating System :: OS Independent
